{
  "ob": {
    "h": {
      "button_vd1": {
        "_chain": {
          "lightness": {
            "high": {
              "bg": {
                "primary": {
                  "default": {
                    "$type": "color",
                    "$value": "#1b6ec2",
                    "$description": "button_vd1 bg raw - lightness:light emphasis:high intent:primary interaction:default"
                  },
                  "hover": {
                    "$type": "color",
                    "$value": "#155a9e",
                    "$description": "button_vd1 bg raw - lightness:light emphasis:high intent:primary interaction:hover"
                  },
                  "active": {
                    "$type": "color",
                    "$value": "#0f4576",
                    "$description": "button_vd1 bg raw - lightness:light emphasis:high intent:primary interaction:active"
                  }
                },
                "secondary": {
                  "default": {
                    "$type": "color",
                    "$value": "#5a6573",
                    "$description": "button_vd1 bg raw - lightness:light emphasis:high intent:secondary interaction:default"
                  },
                  "hover": {
                    "$type": "color",
                    "$value": "#474f5c",
                    "$description": "button_vd1 bg raw - lightness:light emphasis:high intent:secondary interaction:hover"
                  },
                  "active": {
                    "$type": "color",
                    "$value": "#343a44",
                    "$description": "button_vd1 bg raw - lightness:light emphasis:high intent:secondary interaction:active"
                  }
                },
                "tertiary": {
                  "default": {
                    "$type": "color",
                    "$value": "#0e7c7b",
                    "$description": "button_vd1 bg raw - lightness:light emphasis:high intent:tertiary interaction:default"
                  },
                  "hover": {
                    "$type": "color",
                    "$value": "#0a615f",
                    "$description": "button_vd1 bg raw - lightness:light emphasis:high intent:tertiary interaction:hover"
                  },
                  "active": {
                    "$type": "color",
                    "$value": "#064544",
                    "$description": "button_vd1 bg raw - lightness:light emphasis:high intent:tertiary interaction:active"
                  }
                }
              },
              "fg": {
                "primary": {
                  "default": {
                    "$type": "color",
                    "$value": "#ffffff",
                    "$description": "button_vd1 fg raw - lightness:light emphasis:high intent:primary interaction:default"
                  },
                  "hover": {
                    "$type": "color",
                    "$value": "#ffffff",
                    "$description": "button_vd1 fg raw - lightness:light emphasis:high intent:primary interaction:hover"
                  },
                  "active": {
                    "$type": "color",
                    "$value": "#ffffff",
                    "$description": "button_vd1 fg raw - lightness:light emphasis:high intent:primary interaction:active"
                  }
                },
                "secondary": {
                  "default": {
                    "$type": "color",
                    "$value": "#ffffff",
                    "$description": "button_vd1 fg raw - lightness:light emphasis:high intent:secondary interaction:default"
                  },
                  "hover": {
                    "$type": "color",
                    "$value": "#ffffff",
                    "$description": "button_vd1 fg raw - lightness:light emphasis:high intent:secondary interaction:hover"
                  },
                  "active": {
                    "$type": "color",
                    "$value": "#ffffff",
                    "$description": "button_vd1 fg raw - lightness:light emphasis:high intent:secondary interaction:active"
                  }
                },
                "tertiary": {
                  "default": {
                    "$type": "color",
                    "$value": "#ffffff",
                    "$description": "button_vd1 fg raw - lightness:light emphasis:high intent:tertiary interaction:default"
                  },
                  "hover": {
                    "$type": "color",
                    "$value": "#ffffff",
                    "$description": "button_vd1 fg raw - lightness:light emphasis:high intent:tertiary interaction:hover"
                  },
                  "active": {
                    "$type": "color",
                    "$value": "#ffffff",
                    "$description": "button_vd1 fg raw - lightness:light emphasis:high intent:tertiary interaction:active"
                  }
                }
              },
              "border": {
                "primary": {
                  "default": {
                    "$type": "color",
                    "$value": "#1b6ec2",
                    "$description": "button_vd1 border raw - lightness:light emphasis:high intent:primary interaction:default"
                  },
                  "hover": {
                    "$type": "color",
                    "$value": "#155a9e",
                    "$description": "button_vd1 border raw - lightness:light emphasis:high intent:primary interaction:hover"
                  },
                  "active": {
                    "$type": "color",
                    "$value": "#0f4576",
                    "$description": "button_vd1 border raw - lightness:light emphasis:high intent:primary interaction:active"
                  }
                },
                "secondary": {
                  "default": {
                    "$type": "color",
                    "$value": "#5a6573",
                    "$description": "button_vd1 border raw - lightness:light emphasis:high intent:secondary interaction:default"
                  },
                  "hover": {
                    "$type": "color",
                    "$value": "#474f5c",
                    "$description": "button_vd1 border raw - lightness:light emphasis:high intent:secondary interaction:hover"
                  },
                  "active": {
                    "$type": "color",
                    "$value": "#343a44",
                    "$description": "button_vd1 border raw - lightness:light emphasis:high intent:secondary interaction:active"
                  }
                },
                "tertiary": {
                  "default": {
                    "$type": "color",
                    "$value": "#0e7c7b",
                    "$description": "button_vd1 border raw - lightness:light emphasis:high intent:tertiary interaction:default"
                  },
                  "hover": {
                    "$type": "color",
                    "$value": "#0a615f",
                    "$description": "button_vd1 border raw - lightness:light emphasis:high intent:tertiary interaction:hover"
                  },
                  "active": {
                    "$type": "color",
                    "$value": "#064544",
                    "$description": "button_vd1 border raw - lightness:light emphasis:high intent:tertiary interaction:active"
                  }
                }
              }
            },
            "low": {
              "bg": {
                "primary": {
                  "default": {
                    "$type": "color",
                    "$value": "#9cbbda",
                    "$description": "button_vd1 bg raw - lightness:light emphasis:low intent:primary interaction:default"
                  },
                  "hover": {
                    "$type": "color",
                    "$value": "#9ab4ce",
                    "$description": "button_vd1 bg raw - lightness:light emphasis:low intent:primary interaction:hover"
                  },
                  "active": {
                    "$type": "color",
                    "$value": "#98adc0",
                    "$description": "button_vd1 bg raw - lightness:light emphasis:low intent:primary interaction:active"
                  }
                },
                "secondary": {
                  "default": {
                    "$type": "color",
                    "$value": "#b2b8bf",
                    "$description": "button_vd1 bg raw - lightness:light emphasis:low intent:secondary interaction:default"
                  },
                  "hover": {
                    "$type": "color",
                    "$value": "#abb0b7",
                    "$description": "button_vd1 bg raw - lightness:light emphasis:low intent:secondary interaction:hover"
                  },
                  "active": {
                    "$type": "color",
                    "$value": "#a5a9af",
                    "$description": "button_vd1 bg raw - lightness:light emphasis:low intent:secondary interaction:active"
                  }
                },
                "tertiary": {
                  "default": {
                    "$type": "color",
                    "$value": "#98bfc2",
                    "$description": "button_vd1 bg raw - lightness:light emphasis:low intent:tertiary interaction:default"
                  },
                  "hover": {
                    "$type": "color",
                    "$value": "#97b6b8",
                    "$description": "button_vd1 bg raw - lightness:light emphasis:low intent:tertiary interaction:hover"
                  },
                  "active": {
                    "$type": "color",
                    "$value": "#95adaf",
                    "$description": "button_vd1 bg raw - lightness:light emphasis:low intent:tertiary interaction:active"
                  }
                }
              },
              "fg": {
                "primary": {
                  "default": {
                    "$type": "color",
                    "$value": "#232a36",
                    "$description": "button_vd1 fg raw - lightness:light emphasis:low intent:primary interaction:default"
                  },
                  "hover": {
                    "$type": "color",
                    "$value": "#232a36",
                    "$description": "button_vd1 fg raw - lightness:light emphasis:low intent:primary interaction:hover"
                  },
                  "active": {
                    "$type": "color",
                    "$value": "#232a36",
                    "$description": "button_vd1 fg raw - lightness:light emphasis:low intent:primary interaction:active"
                  }
                },
                "secondary": {
                  "default": {
                    "$type": "color",
                    "$value": "#232a36",
                    "$description": "button_vd1 fg raw - lightness:light emphasis:low intent:secondary interaction:default"
                  },
                  "hover": {
                    "$type": "color",
                    "$value": "#232a36",
                    "$description": "button_vd1 fg raw - lightness:light emphasis:low intent:secondary interaction:hover"
                  },
                  "active": {
                    "$type": "color",
                    "$value": "#232a36",
                    "$description": "button_vd1 fg raw - lightness:light emphasis:low intent:secondary interaction:active"
                  }
                },
                "tertiary": {
                  "default": {
                    "$type": "color",
                    "$value": "#232a36",
                    "$description": "button_vd1 fg raw - lightness:light emphasis:low intent:tertiary interaction:default"
                  },
                  "hover": {
                    "$type": "color",
                    "$value": "#232a36",
                    "$description": "button_vd1 fg raw - lightness:light emphasis:low intent:tertiary interaction:hover"
                  },
                  "active": {
                    "$type": "color",
                    "$value": "#232a36",
                    "$description": "button_vd1 fg raw - lightness:light emphasis:low intent:tertiary interaction:active"
                  }
                }
              },
              "border": {
                "primary": {
                  "default": {
                    "$type": "color",
                    "$value": "#9cbbda",
                    "$description": "button_vd1 border raw - lightness:light emphasis:low intent:primary interaction:default"
                  },
                  "hover": {
                    "$type": "color",
                    "$value": "#9ab4ce",
                    "$description": "button_vd1 border raw - lightness:light emphasis:low intent:primary interaction:hover"
                  },
                  "active": {
                    "$type": "color",
                    "$value": "#98adc0",
                    "$description": "button_vd1 border raw - lightness:light emphasis:low intent:primary interaction:active"
                  }
                },
                "secondary": {
                  "default": {
                    "$type": "color",
                    "$value": "#b2b8bf",
                    "$description": "button_vd1 border raw - lightness:light emphasis:low intent:secondary interaction:default"
                  },
                  "hover": {
                    "$type": "color",
                    "$value": "#abb0b7",
                    "$description": "button_vd1 border raw - lightness:light emphasis:low intent:secondary interaction:hover"
                  },
                  "active": {
                    "$type": "color",
                    "$value": "#a5a9af",
                    "$description": "button_vd1 border raw - lightness:light emphasis:low intent:secondary interaction:active"
                  }
                },
                "tertiary": {
                  "default": {
                    "$type": "color",
                    "$value": "#98bfc2",
                    "$description": "button_vd1 border raw - lightness:light emphasis:low intent:tertiary interaction:default"
                  },
                  "hover": {
                    "$type": "color",
                    "$value": "#97b6b8",
                    "$description": "button_vd1 border raw - lightness:light emphasis:low intent:tertiary interaction:hover"
                  },
                  "active": {
                    "$type": "color",
                    "$value": "#95adaf",
                    "$description": "button_vd1 border raw - lightness:light emphasis:low intent:tertiary interaction:active"
                  }
                }
              }
            }
          }
        }
      }
    }
  }
}
