{
  "ob": {
    "h": {
      "button_vd1": {
        "_chain": {
          "surface": {
            "bg": {
              "primary": {
                "default": {
                  "$type": "color",
                  "$value": "{ob.h.button.color.bg.primary.inversity_normal.enabled}",
                  "$description": "button_vd1 bg - intent:primary interaction:default (references the existing button token; surface/theme/emphasis resolved upstream)"
                },
                "hover": {
                  "$type": "color",
                  "$value": "{ob.h.button.color.bg.primary.inversity_normal.hover}",
                  "$description": "button_vd1 bg - intent:primary interaction:hover (references the existing button token; surface/theme/emphasis resolved upstream)"
                },
                "active": {
                  "$type": "color",
                  "$value": "{ob.h.button.color.bg.primary.inversity_normal.pressed}",
                  "$description": "button_vd1 bg - intent:primary interaction:active (references the existing button token; surface/theme/emphasis resolved upstream)"
                }
              },
              "secondary": {
                "default": {
                  "$type": "color",
                  "$value": "{ob.h.button.color.bg.secondary.inversity_normal.enabled}",
                  "$description": "button_vd1 bg - intent:secondary interaction:default (references the existing button token; surface/theme/emphasis resolved upstream)"
                },
                "hover": {
                  "$type": "color",
                  "$value": "{ob.h.button.color.bg.secondary.inversity_normal.hover}",
                  "$description": "button_vd1 bg - intent:secondary interaction:hover (references the existing button token; surface/theme/emphasis resolved upstream)"
                },
                "active": {
                  "$type": "color",
                  "$value": "{ob.h.button.color.bg.secondary.inversity_normal.pressed}",
                  "$description": "button_vd1 bg - intent:secondary interaction:active (references the existing button token; surface/theme/emphasis resolved upstream)"
                }
              },
              "tertiary": {
                "default": {
                  "$type": "color",
                  "$value": "{ob.h.button.color.bg.tertiary.inversity_normal.enabled}",
                  "$description": "button_vd1 bg - intent:tertiary interaction:default (references the existing button token; surface/theme/emphasis resolved upstream)"
                },
                "hover": {
                  "$type": "color",
                  "$value": "{ob.h.button.color.bg.tertiary.inversity_normal.hover}",
                  "$description": "button_vd1 bg - intent:tertiary interaction:hover (references the existing button token; surface/theme/emphasis resolved upstream)"
                },
                "active": {
                  "$type": "color",
                  "$value": "{ob.h.button.color.bg.tertiary.inversity_normal.pressed}",
                  "$description": "button_vd1 bg - intent:tertiary interaction:active (references the existing button token; surface/theme/emphasis resolved upstream)"
                }
              }
            },
            "fg": {
              "primary": {
                "default": {
                  "$type": "color",
                  "$value": "{ob.h.button.color.fg.primary.inversity_normal.enabled}",
                  "$description": "button_vd1 fg - intent:primary interaction:default (references the existing button token; surface/theme/emphasis resolved upstream)"
                },
                "hover": {
                  "$type": "color",
                  "$value": "{ob.h.button.color.fg.primary.inversity_normal.hover}",
                  "$description": "button_vd1 fg - intent:primary interaction:hover (references the existing button token; surface/theme/emphasis resolved upstream)"
                },
                "active": {
                  "$type": "color",
                  "$value": "{ob.h.button.color.fg.primary.inversity_normal.pressed}",
                  "$description": "button_vd1 fg - intent:primary interaction:active (references the existing button token; surface/theme/emphasis resolved upstream)"
                }
              },
              "secondary": {
                "default": {
                  "$type": "color",
                  "$value": "{ob.h.button.color.fg.secondary.inversity_normal.enabled}",
                  "$description": "button_vd1 fg - intent:secondary interaction:default (references the existing button token; surface/theme/emphasis resolved upstream)"
                },
                "hover": {
                  "$type": "color",
                  "$value": "{ob.h.button.color.fg.secondary.inversity_normal.hover}",
                  "$description": "button_vd1 fg - intent:secondary interaction:hover (references the existing button token; surface/theme/emphasis resolved upstream)"
                },
                "active": {
                  "$type": "color",
                  "$value": "{ob.h.button.color.fg.secondary.inversity_normal.pressed}",
                  "$description": "button_vd1 fg - intent:secondary interaction:active (references the existing button token; surface/theme/emphasis resolved upstream)"
                }
              },
              "tertiary": {
                "default": {
                  "$type": "color",
                  "$value": "{ob.h.button.color.fg.tertiary.inversity_normal.enabled}",
                  "$description": "button_vd1 fg - intent:tertiary interaction:default (references the existing button token; surface/theme/emphasis resolved upstream)"
                },
                "hover": {
                  "$type": "color",
                  "$value": "{ob.h.button.color.fg.tertiary.inversity_normal.hover}",
                  "$description": "button_vd1 fg - intent:tertiary interaction:hover (references the existing button token; surface/theme/emphasis resolved upstream)"
                },
                "active": {
                  "$type": "color",
                  "$value": "{ob.h.button.color.fg.tertiary.inversity_normal.pressed}",
                  "$description": "button_vd1 fg - intent:tertiary interaction:active (references the existing button token; surface/theme/emphasis resolved upstream)"
                }
              }
            },
            "border": {
              "primary": {
                "default": {
                  "$type": "color",
                  "$value": "{ob.h.button.color.border.primary.inversity_normal.enabled}",
                  "$description": "button_vd1 border - intent:primary interaction:default (references the existing button token; surface/theme/emphasis resolved upstream)"
                },
                "hover": {
                  "$type": "color",
                  "$value": "{ob.h.button.color.border.primary.inversity_normal.hover}",
                  "$description": "button_vd1 border - intent:primary interaction:hover (references the existing button token; surface/theme/emphasis resolved upstream)"
                },
                "active": {
                  "$type": "color",
                  "$value": "{ob.h.button.color.border.primary.inversity_normal.pressed}",
                  "$description": "button_vd1 border - intent:primary interaction:active (references the existing button token; surface/theme/emphasis resolved upstream)"
                }
              },
              "secondary": {
                "default": {
                  "$type": "color",
                  "$value": "{ob.h.button.color.border.secondary.inversity_normal.enabled}",
                  "$description": "button_vd1 border - intent:secondary interaction:default (references the existing button token; surface/theme/emphasis resolved upstream)"
                },
                "hover": {
                  "$type": "color",
                  "$value": "{ob.h.button.color.border.secondary.inversity_normal.hover}",
                  "$description": "button_vd1 border - intent:secondary interaction:hover (references the existing button token; surface/theme/emphasis resolved upstream)"
                },
                "active": {
                  "$type": "color",
                  "$value": "{ob.h.button.color.border.secondary.inversity_normal.pressed}",
                  "$description": "button_vd1 border - intent:secondary interaction:active (references the existing button token; surface/theme/emphasis resolved upstream)"
                }
              },
              "tertiary": {
                "default": {
                  "$type": "color",
                  "$value": "{ob.h.button.color.border.tertiary.inversity_normal.enabled}",
                  "$description": "button_vd1 border - intent:tertiary interaction:default (references the existing button token; surface/theme/emphasis resolved upstream)"
                },
                "hover": {
                  "$type": "color",
                  "$value": "{ob.h.button.color.border.tertiary.inversity_normal.hover}",
                  "$description": "button_vd1 border - intent:tertiary interaction:hover (references the existing button token; surface/theme/emphasis resolved upstream)"
                },
                "active": {
                  "$type": "color",
                  "$value": "{ob.h.button.color.border.tertiary.inversity_normal.pressed}",
                  "$description": "button_vd1 border - intent:tertiary interaction:active (references the existing button token; surface/theme/emphasis resolved upstream)"
                }
              }
            }
          }
        }
      }
    }
  }
}
